graphmuse/__init__.py
graphmuse/io/__init__.py
graphmuse/io/score_import.py
graphmuse/samplers/base_samplers.py
graphmuse/samplers/csamplers.cpython-311-x86_64-linux-gnu.so
graphmuse/samplers/__init__.py
graphmuse/samplers/sampling_sketch_ext.py
graphmuse/samplers/sampler_functions.py
graphmuse/samplers/sampling_sketch.py
graphmuse/loader/transforms.py
graphmuse/loader/neighbor_loader.py
graphmuse/loader/__init__.py
graphmuse/utils/model_utils.py
graphmuse/utils/graph_utils.py
graphmuse/utils/vocsep.py
graphmuse/utils/__init__.py
graphmuse/utils/graph.py
graphmuse/utils/general.py
graphmuse/utils/features.py
graphmuse/nn/__init__.py
graphmuse/nn/models/pitch_spelling.py
graphmuse/nn/models/metrical_gnn.py
graphmuse/nn/models/__init__.py
graphmuse/nn/models/hgnn.py
graphmuse/nn/models/cadence.py
graphmuse/nn/models/hgvae.py
graphmuse/nn/norm/__init__.py
graphmuse/nn/conv/gat.py
graphmuse/nn/conv/gcn.py
graphmuse/nn/conv/__init__.py
graphmuse/nn/conv/sage.py
graphmuse/nn/conv/musgconv.py
graphmuse/nn/conv/metrical_conv.py
graphmuse/nn/conv/ggru.py
graphmuse/nn/unpool/__init__.py
graphmuse/nn/functional/utils.py
graphmuse/nn/functional/jk.py
graphmuse/nn/functional/__init__.py
graphmuse/nn/pool/__init__.py
graphmuse/nn/pool/heterotopk.py
graphmuse/nn/dense/__init__.py
graphmuse-0.0.5.dist-info/top_level.txt
graphmuse-0.0.5.dist-info/RECORD
graphmuse-0.0.5.dist-info/LICENSE
graphmuse-0.0.5.dist-info/METADATA
graphmuse-0.0.5.dist-info/WHEEL
