Metadata-Version: 2.1
Name: graphmuse
Version: 0.0.5
Summary: GraphMuse is a Python Library for Graph Deep Learning on Symbolic Music.
Author: Emmanouil Karystinaios
Maintainer: Emmanouil Karystinaios
Keywords: deep-learning,symbolic-music,pytorch,geometric-deep-learning,graph-neural-networks,graph-convolutional-networks
Classifier: Development Status :: 1 - Planning
Classifier: Intended Audience :: Developers
Classifier: Intended Audience :: Science/Research
Classifier: Programming Language :: Python :: 3
Classifier: License :: OSI Approved :: MIT License
Classifier: Topic :: Scientific/Engineering :: Artificial Intelligence
Requires-Python: >=3.8
License-File: LICENSE
Requires-Dist: torch
Requires-Dist: torch-geometric
Requires-Dist: torch-sparse
Requires-Dist: torch-scatter
Requires-Dist: torch-cluster
Requires-Dist: pyg-lib
Requires-Dist: numpy >=1.21.0
Requires-Dist: partitura >=1.5.0
Requires-Dist: psutil ==5.9.5
